{"is_source_file": true, "format": "JavaScript (React JSX)", "description": "This file is the entry point for a React-based web application. It imports essential React libraries, application components, and CSS. The code initializes the React DOM rendering process by attaching the React app to the DOM element with id 'root' and renders the App component within React.StrictMode for development checks.", "external_files": ["./App", "./index.css"], "external_methods": ["ReactDOM.createRoot", "root.render"], "published": [], "classes": [], "methods": [{"name": "ReactDOM.createRoot", "description": "Creates a root for React rendering in the specified DOM element."}, {"name": "root.render", "description": "Renders the React element tree into the DOM."}], "calls": ["ReactDOM.createRoot", "root.render", "document.getElementById", "React.StrictMode", "<App />"], "search-terms": ["ReactDOM", "createRoot", "render", "strict mode", "index.js", "entry point"], "state": 2, "file_id": 11, "knowledge_revision": 25, "git_revision": "e705284a8782ff37ffc884450f0295d5de79233e", "ctags": [{"_type": "tag", "name": "root", "path": "/home/kavia/workspace/code-generation/web-app-scaffold-185385-185394/frontend_web_app/src/index.js", "pattern": "/^const root = ReactDOM.createRoot(document.getElementById('root'));$/", "language": "JavaScript", "kind": "constant"}], "hash": "9fc5841375336fc175b49f8767a11383", "format-version": 4, "code-base-name": "frontend_web_app", "filename": "frontend_web_app/src/index.js", "revision_history": [{"25": "e705284a8782ff37ffc884450f0295d5de79233e"}]}